one/__init__.py
one/__main__.py
one/one.py
one/commands/__init__.py
one/commands/app.py
one/commands/auth.py
one/commands/aws.py
one/commands/init.py
one/commands/shell.py
one/commands/terraform.py
one/commands/workspace.py
one/docker/__init__.py
one/docker/client.py
one/docker/container.py
one/docker/image.py
one/prompt/__init__.py
one/prompt/auth.py
one/prompt/idp.py
one/prompt/init.py
one/utils/__init__.py
one/utils/config.py
one/utils/operators.py
one/utils/parse_env.py
one/utils/plugins.py
one/utils/print_progress_bar.py
one/utils/prompt.py
one/utils/terraform_modules.py
one/utils/app/__init__.py
one/utils/app/common.py
one/utils/app/deploy/__init__.py
one/utils/app/deploy/ecs.py
one/utils/app/deploy/static.py
one/utils/app/registry/__init__.py
one/utils/app/registry/ecr.py
one/utils/environment/__init__.py
one/utils/environment/aws.py
one/utils/environment/common.py
one/utils/environment/idp.py
one_cli-0.7.2.dist-info/LICENSE
one_cli-0.7.2.dist-info/METADATA
one_cli-0.7.2.dist-info/WHEEL
one_cli-0.7.2.dist-info/entry_points.txt
one_cli-0.7.2.dist-info/top_level.txt
one_cli-0.7.2.dist-info/RECORD
