Metadata-Version: 2.1
Name: one-cli
Version: 0.7.2
Summary: Python CLI to manage stacks from DNX.
Home-page: https://github.com/DNXLabs/one-cli
Author: DNX Solutions
Author-email: contact@dnx.solutions
License: Apache License 2.0
Platform: UNKNOWN
Classifier: Development Status :: 5 - Production/Stable
Classifier: Intended Audience :: Developers
Classifier: Intended Audience :: System Administrators
Classifier: Natural Language :: English
Classifier: License :: OSI Approved :: Apache Software License
Classifier: Programming Language :: Python
Classifier: Programming Language :: Python :: 3
Classifier: Programming Language :: Python :: 3.4
Classifier: Programming Language :: Python :: 3.5
Classifier: Programming Language :: Python :: 3.6
Classifier: Programming Language :: Python :: 3.7
Classifier: Programming Language :: Python :: 3.8
Requires-Python: >=3.6
Requires-Dist: altgraph (==0.17)
Requires-Dist: certifi (==2020.4.5.1)
Requires-Dist: chardet (==4.0.0)
Requires-Dist: click (==7.1.2)
Requires-Dist: docker-py (==1.10.6)
Requires-Dist: docker-pycreds (==0.4.0)
Requires-Dist: dockerpty (==0.4.1)
Requires-Dist: idna (==2.9)
Requires-Dist: prompt-toolkit (==1.0.14)
Requires-Dist: Pygments (==2.6.1)
Requires-Dist: PyInquirer (==1.0.3)
Requires-Dist: PyInstaller (==3.6)
Requires-Dist: python-dotenv (==0.13.0)
Requires-Dist: PyYAML (==5.3.1)
Requires-Dist: regex (==2020.5.7)
Requires-Dist: requests (==2.25.1)
Requires-Dist: six (==1.14.0)
Requires-Dist: urllib3 (==1.25.9)
Requires-Dist: wcwidth (==0.1.9)
Requires-Dist: websocket-client (==0.57.0)
Requires-Dist: packaging (==20.4)
